docker_tool/__init__.py
docker_tool/cli.py
docker_tool/docker_client.py
docker_tool/utils.py
docker_tool/version.py
docker_tool/wizard.py
docker_tool-1.0.4.dist-info/licenses/LICENSE
docker_tool-1.0.4.dist-info/METADATA
docker_tool-1.0.4.dist-info/WHEEL
docker_tool-1.0.4.dist-info/entry_points.txt
docker_tool-1.0.4.dist-info/top_level.txt
docker_tool-1.0.4.dist-info/RECORD
