Metadata-Version: 2.4
Name: docker-tool
Version: 1.0.4
Summary: 🛠️ Simple and interactive CLI for Docker container management
Author-email: JuleZ <julestblt.dev@pm.me>
License-Expression: MIT
Project-URL: Homepage, https://github.com/Julestblt/docker-wrapper
Project-URL: Repository, https://github.com/Julestblt/docker-wrapper
Requires-Python: >=3.9
License-File: LICENSE
Requires-Dist: typer>=0.9.0
Requires-Dist: rich>=13.7.0
Requires-Dist: questionary>=2.0.1
Requires-Dist: prompt-toolkit>=3.0.43
Requires-Dist: docker>=7.0.0
Provides-Extra: dev
Requires-Dist: pytest>=7.0.0; extra == "dev"
Requires-Dist: pytest-cov>=4.0.0; extra == "dev"
Requires-Dist: pytest-mock>=3.0.0; extra == "dev"
Requires-Dist: coverage>=7.0.0; extra == "dev"
Requires-Dist: black>=23.0.0; extra == "dev"
Requires-Dist: flake8>=6.0.0; extra == "dev"
Requires-Dist: mypy>=1.0.0; extra == "dev"
Requires-Dist: build>=0.10.0; extra == "dev"
Requires-Dist: twine>=4.0.0; extra == "dev"
Provides-Extra: test
Requires-Dist: pytest>=7.0.0; extra == "test"
Requires-Dist: pytest-cov>=4.0.0; extra == "test"
Requires-Dist: pytest-mock>=3.0.0; extra == "test"
Requires-Dist: coverage>=7.0.0; extra == "test"
Dynamic: license-file
